formatter/__init__.py
formatter/clauses.py
formatter/formatter.py
formatter/functions.py
formatter/identation.py
tests/__init__.py
tests/test_clauses.py
tests/test_formatter.py
tests/test_functions.py
tests/test_identation.py
simple_sql_formatter-1.dist-info/LICENSE
simple_sql_formatter-1.dist-info/METADATA
simple_sql_formatter-1.dist-info/WHEEL
simple_sql_formatter-1.dist-info/top_level.txt
simple_sql_formatter-1.dist-info/RECORD
