Metadata-Version: 2.1
Name: simple-sql-formatter
Version: 1
Summary: Simple SQL Formatter
Home-page: https://github.com/natansilva/sql_formatter
Author: Natan Anael
Author-email: natan.anael@gmail.com
License: UNKNOWN
Platform: UNKNOWN
Classifier: Programming Language :: Python :: 3
Classifier: License :: OSI Approved :: MIT License
Classifier: Operating System :: OS Independent
